sophus_pyo3-0.6.1.dist-info/METADATA
sophus_pyo3-0.6.1.dist-info/WHEEL
sophus_pyo3/__init__.py
sophus_pyo3/sophus_pyo3.abi3.so
sophus_pyo3-0.6.1.dist-info/RECORD
