Metadata-Version: 2.3
Name: sophus_pyo3
Version: 0.6.1
Summary: sophus - geometry for robotics and computer vision
Keywords: robotics,optimization
License: MIT OR Apache-2.0
Project-URL: Source Code, https://github.com/farm-ng/sophus-rs/
